{
  "settings": {
    "migrated": 6,
    "iconPacksPath": ".obsidian/icons",
    "fontSize": 16,
    "emojiStyle": "native",
    "iconColor": null,
    "recentlyUsedIcons": [
      "LiSquirrel",
      "LiPenBox",
      "📓",
      "LiSheet",
      "LiHelpingHand"
    ],
    "recentlyUsedIconsSize": 5,
    "rules": [
      {
        "rule": "2024*",
        "icon": "📓",
        "for": "everything",
        "order": 0
      },
      {
        "rule": ".*SQL.*",
        "icon": "LiSquirrel",
        "for": "everything",
        "order": 1,
        "color": "#4016da",
        "useFilePath": true
      }
    ],
    "extraMargin": {
      "top": 0,
      "right": 4,
      "bottom": 0,
      "left": 0
    },
    "iconInTabsEnabled": true,
    "iconInTitleEnabled": true,
    "iconInTitlePosition": "inline",
    "iconInFrontmatterEnabled": true,
    "iconInFrontmatterFieldName": "icon",
    "iconColorInFrontmatterFieldName": "iconColor",
    "iconsBackgroundCheckEnabled": false,
    "iconsInNotesEnabled": true,
    "iconsInLinksEnabled": true,
    "iconIdentifier": ":",
    "lucideIconPackType": "native",
    "debugMode": false
  },
  "docs": "LiBookText",
  "docs/tutorial": "LiHelpingHand",
  "meteomarche_fulldata.2021-12-10-12-59": "LiSheet",
  "notes": "📓",
  "draft": "LiPenBox",
  "datastructures/Data structures.md": "LiSheet"
}